captcha/__init__.py
captcha/apps.py
captcha/fields.py
captcha/forms.py
captcha/settings.py
captcha/utils.py
captcha/version.py
captcha/widgets.py
captcha/locale/en/LC_MESSAGES/django.mo
captcha/locale/en/LC_MESSAGES/django.po
captcha/locale/it/LC_MESSAGES/django.mo
captcha/locale/it/LC_MESSAGES/django.po
captcha/templates/captcha/widgets/captcha.html
django_fluo_captcha-0.1.1.dist-info/COPYING
django_fluo_captcha-0.1.1.dist-info/METADATA
django_fluo_captcha-0.1.1.dist-info/WHEEL
django_fluo_captcha-0.1.1.dist-info/top_level.txt
django_fluo_captcha-0.1.1.dist-info/RECORD
